{
    "officialAccounts": "Official Accounts",
    "back": "Back",
    "profile": "Profile",
    "done": "Done",
    "edit": "Edit",
    "settings": "Settings",
    "theMinValueBiggerThenMaxValue": "The min value for the range should be smaller then the max value",
    "thePropertyWithMinMaxRangeError": "The property with [min-max] range can have only two numbers",
    "invalidProperty": "Invalid {property}",
    "optional": "optional",
    "thisFieldIsRequired": "This field is required",
    "Invalid_1": "Invalid {1}",
    "pleaseDrawPassword": "Please draw a gesture password",
    "drawYourPassword": "Draw your gesture password",
    "gestureNotRecognized": "Gesture not recognized, please try again",
    "pleaseDrawPattern": "Please draw a pattern",
    "drawYourPattern": "Draw your pattern",
    "pleaseDrawYourPatternAgain": "Please draw your pattern again",
    "invalidPattern": "Invalid pattern, please try again",
    "patternNotMatching": "Patterns didn\\'t match. Please start again",
    "wrongPattern": "Wrong pattern",
    "correctGesture": "Correct gesture detected",
    "authenticationFailed": "Authentication failed",
    "pleaseRestartTIM": "Please restart TiM",
    "cancel": "Cancel",
    "details": "Details",
    "addServerUrl": "Add server url",
    "search": "Search",
    "listOfProducts": "Click for a list of products",
    "hello": "Hello {1}!",  // {1} is the first name of the customer
    "testForgetMe": "This is a test mechanism to reset all communications with this provider",
    "confirmForgetMe": "Are you sure you want \\'{1}\\' to forget you", //{1} is the bank name
    "forgetMe": "Forget me",
    "iNeed": "I need...",
    "LivingWithParents": "Living with parents",
    "HomeOwnerWithMortgage": "Home owner (with mortgage)",
    "HomeOwnerWithoutMortgage": "Home owner (without mortgage)",
    "TenantPrivate":  "Tenant (private)",
    "TenantCounsel": "Tenant (counsel)",
    "BenefitPayments": "Benefit Payments",
    "BillsExpenses": "Bills / Expenses",
    "CapitalRaisingScottishWidowsBank": "Capital Raising ( Scottish Widows Bank )",
    "Inheritance": "Inheritance",
    "ProbateExecutorTrustee": "Probate / Executor / Trustee",
    "SalaryPensionOtherRegularIncome" : "Salary / Pension / Other Regular Income",
    "Savings": "Savings",
    "SpendingMoney": "Spending Money",
    "Student": "Student",
    "Home": "Home",
    "Mobile": "Mobile",
    "Work": "Work",
    "newProduct": "New product",
    "tapToRemovePhotos": "Tap to remove photos",
    "addNew": "Add new {1}", // {1} is items property type like 'tradle.Profile' for property 'contacts' of 'tradle.Organization'
}
